README
setup.cfg
setup.py
textcatcher.py
textcatcher.egg-info/PKG-INFO
textcatcher.egg-info/SOURCES.txt
textcatcher.egg-info/dependency_links.txt
textcatcher.egg-info/top_level.txt